tweetSentimentAnalysis_MP/__init__.py
tweetSentimentAnalysis_MP/assignment10.py
tweetSentimentAnalysis_MP/examples/__init__.py
tweetSentimentAnalysis_MP/examples/example1.py
tweetSentimentAnalysis_MP/examples/example2.py
tweetSentimentAnalysis_MP-0.0.2.dist-info/LICENSE
tweetSentimentAnalysis_MP-0.0.2.dist-info/METADATA
tweetSentimentAnalysis_MP-0.0.2.dist-info/WHEEL
tweetSentimentAnalysis_MP-0.0.2.dist-info/top_level.txt
tweetSentimentAnalysis_MP-0.0.2.dist-info/RECORD
