Metadata-Version: 2.1
Name: tweetSentimentAnalysis_MP
Version: 0.0.2
Summary: Assignment #10
Author-email: Matthew Postel <mpostel@g.emporia.edu>
Project-URL: Homepage, https://github.com/BadWolf22
Classifier: Programming Language :: Python :: 3
Classifier: License :: OSI Approved :: MIT License
Classifier: Operating System :: OS Independent
Requires-Python: >=3.7
License-File: LICENSE
